clipipe.py
clipipe-0.1.0.dist-info/METADATA
clipipe-0.1.0.dist-info/WHEEL
clipipe-0.1.0.dist-info/entry_points.txt
clipipe-0.1.0.dist-info/RECORD
