Metadata-Version: 2.4
Name: clipipe
Version: 0.1.0
Summary: Send and receive data using human-readable codes
Project-URL: Homepage, https://clipipe.io
Project-URL: Issues, https://github.com/amirkarimi/clipipe/issues
Author-email: Amir Karimi <me@amirkarimi.dev>
Keywords: bash,pipe,utilities
Classifier: License :: OSI Approved :: MIT License
Classifier: Operating System :: POSIX
Classifier: Programming Language :: Python :: 3
Classifier: Topic :: Utilities
Requires-Python: >=3.10
Requires-Dist: click>=8.2.1
Requires-Dist: requests>=2.32.4
Requires-Dist: rich>=14.1.0
